{"cachedDefinitions":[],"cachedSynonyms":[{"content":[],"api":"Free Dictionary API","word":"Passphrase","lang":"en_US"},{"content":[],"api":"Free Dictionary API","word":"y","lang":"en_US"},{"content":[{"word":"right here"}],"api":"Free Dictionary API","word":"here","lang":"en_US"},{"content":[],"api":"Free Dictionary API","word":"h","lang":"en_US"},{"content":[],"api":"Free Dictionary API","word":"mitigate","lang":"en_US"},{"content":[],"api":"Free Dictionary API","word":"reporting","lang":"en_US"},{"content":[],"api":"Free Dictionary API","word":"empty","lang":"en_US"},{"content":[],"api":"Free Dictionary API","word":"A","lang":"en_US"},{"content":[],"api":"Free Dictionary API","word":"below","lang":"en_US"},{"content":[],"api":"Free Dictionary API","word":"v","lang":"en_US"},{"content":[],"api":"Free Dictionary API","word":"Answer","lang":"en_US"},{"content":[],"api":"Free Dictionary API","word":"site","lang":"en_US"},{"content":[],"api":"Free Dictionary API","word":"ar","lang":"en_US"},{"content":[],"api":"Free Dictionary API","word":"guidance","lang":"en_US"},{"content":[],"api":"Free Dictionary API","word":"l","lang":"en_US"},{"content":[],"api":"Free Dictionary API","word":"Escalation","lang":"en_US"},{"content":[],"api":"Free Dictionary API","word":"Authorities","lang":"en_US"},{"content":[],"api":"Free Dictionary API","word":"Playbooks","lang":"en_US"},{"content":[],"api":"Free Dictionary API","word":"Availability","lang":"en_US"},{"content":[],"api":"Free Dictionary API","word":"Confidentiality","lang":"en_US"},{"content":[],"api":"Free Dictionary API","word":"Integrity","lang":"en_US"},{"content":[],"api":"Free Dictionary API","word":"Installing","lang":"en_US"},{"content":[],"api":"Free Dictionary API","word":"Troubleshooting","lang":"en_US"},{"content":[],"api":"Free Dictionary API","word":"Enumeration","lang":"en_US"},{"content":[],"api":"Free Dictionary API","word":"questions","lang":"en_US"},{"content":[],"api":"Free Dictionary API","word":"p","lang":"en_US"},{"content":[],"api":"Free Dictionary API","word":"vuln","lang":"en_US"},{"content":[],"api":"Free Dictionary API","word":"W","lang":"en_US"},{"content":[],"api":"Free Dictionary API","word":"directory","lang":"en_US"},{"content":[],"api":"Free Dictionary API","word":"draft","lang":"en_US"},{"content":[],"api":"Free Dictionary API","word":"UPDATE","lang":"en_US"},{"content":[],"api":"Free Dictionary API","word":"admin","lang":"en_US"},{"content":[],"api":"Free Dictionary API","word":"ongoing","lang":"en_US"},{"content":[{"word":"affix"},{"word":"join"},{"word":"put together"},{"word":"unite"}],"api":"Free Dictionary API","word":"Connect","lang":"en_US"},{"content":[],"api":"Free Dictionary API","word":"Description","lang":"en_US"},{"content":[],"api":"Free Dictionary API","word":"title","lang":"en_US"},{"content":[{"word":"barrier"},{"word":"blockage"},{"word":"obstruction"}],"api":"Free Dictionary API","word":"Block","lang":"en_US"},{"content":[],"api":"Free Dictionary API","word":"Overview","lang":"en_US"},{"content":[],"api":"Free Dictionary API","word":"date","lang":"en_US"},{"content":[],"api":"Free Dictionary API","word":"definition","lang":"en_US"},{"content":[],"api":"Free Dictionary API","word":"b","lang":"en_US"},{"content":[],"api":"Free Dictionary API","word":"Basics","lang":"en_US"},{"content":[{"word":"s.ap."},{"word":"yeartide"},{"word":"yeartime"},{"word":"series (British English)"}],"api":"Free Dictionary API","word":"s","lang":"en_US"},{"content":[],"api":"Free Dictionary API","word":"C","lang":"en_US"},{"content":[],"api":"Free Dictionary API","word":"des","lang":"en_US"},{"content":[],"api":"Free Dictionary API","word":"Monitoring","lang":"en_US"},{"content":[],"api":"Free Dictionary API","word":"ng","lang":"en_US"},{"content":[],"api":"Free Dictionary API","word":"packet","lang":"en_US"},{"content":[],"api":"Free Dictionary API","word":"connections","lang":"en_US"},{"content":[],"api":"Free Dictionary API","word":"HYDRA","lang":"en_US"},{"content":[],"api":"Free Dictionary API","word":"wi","lang":"en_US"},{"content":[],"api":"Free Dictionary API","word":"e","lang":"en_US"},{"content":[],"api":"Free Dictionary API","word":"twitter","lang":"en_US"},{"content":[],"api":"Free Dictionary API","word":"o","lang":"en_US"},{"content":[],"api":"Free Dictionary API","word":"session","lang":"en_US"},{"content":[{"word":"shell-like"}],"api":"Free Dictionary API","word":"shell","lang":"en_US"},{"content":[],"api":"Free Dictionary API","word":"bash","lang":"en_US"},{"content":[],"api":"Free Dictionary API","word":"Status","lang":"en_US"},{"content":[],"api":"Free Dictionary API","word":"Source","lang":"en_US"},{"content":[],"api":"Free Dictionary API","word":"Version","lang":"en_US"},{"content":[],"api":"Free Dictionary API","word":"target","lang":"en_US"},{"content":[],"api":"Free Dictionary API","word":"cybersecurity","lang":"en_US"},{"content":[],"api":"Free Dictionary API","word":"my","lang":"en_US"},{"content":[{"word":"heap"},{"word":"mass"},{"word":"pile"}],"api":"Free Dictionary API","word":"amass","lang":"en_US"},{"content":[],"api":"Free Dictionary API","word":"f","lang":"en_US"},{"content":[],"api":"Free Dictionary API","word":"oo","lang":"en_US"},{"content":[],"api":"Free Dictionary API","word":"Tools","lang":"en_US"},{"content":[],"api":"Free Dictionary API","word":"ock","lang":"en_US"},{"content":[],"api":"Free Dictionary API","word":"i","lang":"en_US"},{"content":[],"api":"Free Dictionary API","word":"thoughts","lang":"en_US"},{"content":[],"api":"Free Dictionary API","word":"os","lang":"en_US"},{"content":[],"api":"Free Dictionary API","word":"Explanation","lang":"en_US"},{"content":[],"api":"Free Dictionary API","word":"disabled","lang":"en_US"},{"content":[{"word":"beclothe"},{"word":"dight"},{"word":"put on"},{"word":"put the moves on"},{"word":"romance"}],"api":"Free Dictionary API","word":"addresses","lang":"en_US"},{"content":[],"api":"Free Dictionary API","word":"ILL","lang":"en_US"},{"content":[],"api":"Free Dictionary API","word":"Domain","lang":"en_US"},{"content":[],"api":"Free Dictionary API","word":"45","lang":"en_US"},{"content":[{"word":"anonymous"},{"word":"obscure"},{"word":"unascertained"},{"word":"uncharted"},{"word":"undiscovered"},{"word":"unexplored"},{"word":"unfamiliar"},{"word":"unidentified"},{"word":"unnamed"},{"word":"unrecognized"},{"word":"unrevealed"},{"word":"unsung"}],"api":"Free Dictionary API","word":"unknown","lang":"en_US"},{"content":[{"word":"stoup"}],"api":"Free Dictionary API","word":"Fonts","lang":"en_US"},{"content":[],"api":"Free Dictionary API","word":"Themes","lang":"en_US"},{"content":[{"word":"bold"},{"word":"daring"},{"word":"doughty"},{"word":"orped"},{"word":"resilient"},{"word":"stalwart"}],"api":"Free Dictionary API","word":"Brave","lang":"en_US"},{"content":[],"api":"Free Dictionary API","word":"KS","lang":"en_US"},{"content":[],"api":"Free Dictionary API","word":"OTHER","lang":"en_US"},{"content":[{"word":"aspect"},{"word":"mien"}],"api":"Free Dictionary API","word":"Appearance","lang":"en_US"},{"content":[],"api":"Free Dictionary API","word":"Identical","lang":"en_US"},{"content":[],"api":"Free Dictionary API","word":"Similar","lang":"en_US"},{"content":[],"api":"Free Dictionary API","word":"console","lang":"en_US"},{"content":[],"api":"Free Dictionary API","word":"Install","lang":"en_US"},{"content":[{"word":"anguish"},{"word":"harrow"},{"word":"martyr"},{"word":"tantalise"},{"word":"tantalize"},{"word":"torment"},{"word":"trouble"},{"word":"vex"},{"word":"distrain"},{"word":"age"},{"word":"antique"},{"word":"patinate"}],"api":"Free Dictionary API","word":"DISTRESS","lang":"en_US"},{"content":[],"api":"Free Dictionary API","word":"modules","lang":"en_US"},{"content":[],"api":"Free Dictionary API","word":"commands","lang":"en_US"},{"content":[{"word":"accomplish"},{"word":"carry out"},{"word":"functionate"},{"word":"serve"},{"word":"imitate"},{"word":"personate"},{"word":"take off"},{"word":"do in"},{"word":"murder"},{"word":"off"},{"word":"rub out"},{"word":"go to bed with"},{"word":"sleep with"},{"word":"defraud"},{"word":"diddle"},{"word":"mug off"},{"word":"rip off"},{"word":"scam"},{"word":"attend"},{"word":"serve"},{"word":"wait on"},{"word":"furnish"},{"word":"give"},{"word":"supply"}],"api":"Free Dictionary API","word":"done","lang":"en_US"},{"content":[{"word":"male"},{"word":"manly"},{"word":"virile"},{"word":"instant"},{"word":"jiffy"},{"word":"mo"},{"word":"moment"},{"word":"sec"},{"word":"second"},{"word":"tic"},{"word":"minute of arc"}],"api":"Free Dictionary API","word":"m","lang":"en_US"},{"content":[],"api":"Free Dictionary API","word":"output","lang":"en_US"},{"content":[],"api":"Free Dictionary API","word":"framework","lang":"en_US"},{"content":[],"api":"Free Dictionary API","word":"doc","lang":"en_US"},{"content":[{"word":"dec"}],"api":"Free Dictionary API","word":"d","lang":"en_US"},{"content":[],"api":"Free Dictionary API","word":"ALL","lang":"en_US"},{"content":[{"word":"matter"},{"word":"doodad"},{"word":"thingamabob"},{"word":"dope"},{"word":"gear"},{"word":"garbage"},{"word":"rubbish"},{"word":"feed one's face"},{"word":"fill one's face"},{"word":"stuff one's face"},{"word":"fuck"},{"word":"root"},{"word":"screw"}],"api":"Free Dictionary API","word":"Stuff","lang":"en_US"},{"content":[{"word":"matter"},{"word":"doodad"},{"word":"thingamabob"},{"word":"dope"},{"word":"gear"},{"word":"garbage"},{"word":"rubbish"},{"word":"feed one's face"},{"word":"fill one's face"},{"word":"stuff one's face"},{"word":"fuck"},{"word":"root"},{"word":"screw"}],"api":"Free Dictionary API","word":"Stuff","lang":"en_US"},{"content":[{"word":"matter"},{"word":"doodad"},{"word":"thingamabob"},{"word":"dope"},{"word":"gear"},{"word":"garbage"},{"word":"rubbish"},{"word":"feed one's face"},{"word":"fill one's face"},{"word":"stuff one's face"},{"word":"fuck"},{"word":"root"},{"word":"screw"}],"api":"Free Dictionary API","word":"Stuff","lang":"en_US"},{"content":[{"word":"frob"},{"word":"tweak"},{"word":"crack"}],"api":"Free Dictionary API","word":"hacking","lang":"en_US"},{"content":[],"api":"Free Dictionary API","word":"awesome","lang":"en_US"}]}